EqUMP/__init__.py
EqUMP/base/__init__.py
EqUMP/base/estimation.py
EqUMP/base/irf.py
EqUMP/base/plot.py
EqUMP/base/qudarature.py
EqUMP/base/trf.py
EqUMP/equating/__init__.py
EqUMP/equating/TSE/tse.py
EqUMP/equating/kernel/.gitkeep
EqUMP/equating/kernel/__init__.py
EqUMP/equating/obs/.gitkeep
EqUMP/extensions/__init__.py
EqUMP/extensions/PARSCALE/parscaleparser.py
EqUMP/extensions/STUIRT/stuirtparser.py
EqUMP/extensions/flexMIRT/.gitkeep
EqUMP/linking/__init__.py
EqUMP/linking/helper.py
EqUMP/linking/HB/Haebara.py
EqUMP/linking/MM/mean_mean.py
EqUMP/linking/MS/mean_sigma.py
EqUMP/linking/SL/Stocking_Lord.py
EqUMP/scoring/__init__.py
EqUMP/sem/bootsrapping/.gitkeep
EqUMP/sem/delta/.gitkeep
EqUMP/tests/__init__.py
EqUMP/tests/rbridge.py
EqUMP/tests/test_rbridge.py
EqUMP/tests/base/test_estimation.py
EqUMP/tests/base/test_irf.py
EqUMP/tests/base/test_irf_class.py
EqUMP/tests/base/test_irf_custom_scoring.py
EqUMP/tests/base/test_irf_validation.py
EqUMP/tests/base/test_plot.py
EqUMP/tests/base/test_trf.py
EqUMP/tests/equating/test_true_score.py
EqUMP/tests/equating_error/.gitkeep
EqUMP/tests/equating_error/test_equating_error.py
EqUMP/tests/extensions/.gitkeep
EqUMP/tests/linking/KBformX_par.csv
EqUMP/tests/linking/KBformY_par.csv
EqUMP/tests/linking/SNSequate.R
EqUMP/tests/linking/helper.py
EqUMP/tests/linking/test_backward_compat.py
EqUMP/tests/linking/HB/test_linking_hb.py
EqUMP/tests/linking/MM/test_linking_mm.py
EqUMP/tests/linking/MS/test_linking_ms.py
EqUMP/tests/linking/SL/SL_onedirect.R
EqUMP/tests/linking/SL/test_linking_sl.py
EqUMP/tests/linking/SL/test_production_scenario.py
EqUMP/tests/scoring/__init__.py
EqUMP/tests/sem/__init__.py
EqUMP/utils/.gitkeep
eqump-0.3.5.dist-info/METADATA
eqump-0.3.5.dist-info/WHEEL
eqump-0.3.5.dist-info/licenses/LICENSE
eqump-0.3.5.dist-info/RECORD
