Metadata-Version: 2.4
Name: EqUMP
Version: 0.3.5
Summary: IRT Equating for Unidimensional Mixed Format Test with Python
Project-URL: Repository, https://github.com/huni1023/EqUMP
Author-email: JeeHun Sung <jhun1023@naver.com>, YoungJin Kim <edu.yj.kim@gmail.com>, Hoon Kim <h000000nkim@gmail.com>, YeJin Woo <wooye6093@gmail.com>
License: MIT
License-File: LICENSE
Keywords: educational measurement,item response theory,linking,mixed format test,test equating
Requires-Python: <3.14,>=3.9
Requires-Dist: matplotlib>=3.9.4
Requires-Dist: numpy>=2.0.2
Requires-Dist: pandas>=2.3.1
Requires-Dist: python-dotenv>=1.1.1
Requires-Dist: scipy>=1.13.1
Provides-Extra: dev
Requires-Dist: black>=25.1.0; extra == 'dev'
Requires-Dist: pytest>=8.4.1; extra == 'dev'
